synthai/__init__.py
synthai/cli.py
synthai/core/__init__.py
synthai/core/base.py
synthai/core/config.py
synthai/core/generator.py
synthai/evaluators/__init__.py
synthai/evaluators/diversity_evaluator.py
synthai/evaluators/quality_evaluator.py
synthai/generators/__init__.py
synthai/generators/tabular_generator.py
synthai/generators/text_generator.py
synthai/utils/__init__.py
synthai_generator-0.1.0.dist-info/licenses/LICENSE
synthai_generator-0.1.0.dist-info/METADATA
synthai_generator-0.1.0.dist-info/WHEEL
synthai_generator-0.1.0.dist-info/entry_points.txt
synthai_generator-0.1.0.dist-info/top_level.txt
synthai_generator-0.1.0.dist-info/RECORD
